nionswift_plugin/nionswift_video_capture/VideoCapture.py
nionswift_plugin/nionswift_video_capture/__init__.py
nionswift_video_capture-2.7.1.dist-info/licenses/LICENSE
nionswift_video_capture-2.7.1.dist-info/METADATA
nionswift_video_capture-2.7.1.dist-info/WHEEL
nionswift_video_capture-2.7.1.dist-info/top_level.txt
nionswift_video_capture-2.7.1.dist-info/RECORD
