Metadata-Version: 2.4
Name: nionswift-video-capture
Version: 2.7.1
Summary: Capture video from built-in camera using OpenCV.
Home-page: https://github.com/nion-software/nionswift-hyperspy
Author: Nion Software
Author-email: swift@nion.com
License: GPL-3.0-only
Classifier: Development Status :: 5 - Production/Stable
Classifier: License :: OSI Approved :: GNU General Public License v3 (GPLv3)
Classifier: Programming Language :: Python :: 3.11
Classifier: Programming Language :: Python :: 3.12
Classifier: Programming Language :: Python :: 3.13
Requires-Python: >=3.11
License-File: LICENSE
Requires-Dist: nionswift-instrumentation<24.0,>=23.4
Requires-Dist: nionswift<17.0,>=16.15
Dynamic: license-file
